mkdocs_swan/404.html
mkdocs_swan/__init__.py
mkdocs_swan/main.html
mkdocs_swan/mkdocs_theme.yml
mkdocs_swan/notebook.html
mkdocs_swan/css/fonts.css
mkdocs_swan/css/notebook.css
mkdocs_swan/css/style.css
mkdocs_swan/css/fonts/KFOjCnqEu92Fr1Mu51TjASc-CsTKlA.woff2
mkdocs_swan/css/fonts/KFOjCnqEu92Fr1Mu51TjASc0CsTKlA.woff2
mkdocs_swan/css/fonts/KFOjCnqEu92Fr1Mu51TjASc1CsTKlA.woff2
mkdocs_swan/css/fonts/KFOjCnqEu92Fr1Mu51TjASc2CsTKlA.woff2
mkdocs_swan/css/fonts/KFOjCnqEu92Fr1Mu51TjASc3CsTKlA.woff2
mkdocs_swan/css/fonts/KFOjCnqEu92Fr1Mu51TjASc5CsTKlA.woff2
mkdocs_swan/css/fonts/KFOjCnqEu92Fr1Mu51TjASc6CsQ.woff2
mkdocs_swan/css/fonts/KFOjCnqEu92Fr1Mu51TzBic-CsTKlA.woff2
mkdocs_swan/css/fonts/KFOjCnqEu92Fr1Mu51TzBic0CsTKlA.woff2
mkdocs_swan/css/fonts/KFOjCnqEu92Fr1Mu51TzBic1CsTKlA.woff2
mkdocs_swan/css/fonts/KFOjCnqEu92Fr1Mu51TzBic2CsTKlA.woff2
mkdocs_swan/css/fonts/KFOjCnqEu92Fr1Mu51TzBic3CsTKlA.woff2
mkdocs_swan/css/fonts/KFOjCnqEu92Fr1Mu51TzBic5CsTKlA.woff2
mkdocs_swan/css/fonts/KFOjCnqEu92Fr1Mu51TzBic6CsQ.woff2
mkdocs_swan/css/fonts/KFOkCnqEu92Fr1Mu51xEIzIFKw.woff2
mkdocs_swan/css/fonts/KFOkCnqEu92Fr1Mu51xFIzIFKw.woff2
mkdocs_swan/css/fonts/KFOkCnqEu92Fr1Mu51xGIzIFKw.woff2
mkdocs_swan/css/fonts/KFOkCnqEu92Fr1Mu51xHIzIFKw.woff2
mkdocs_swan/css/fonts/KFOkCnqEu92Fr1Mu51xIIzI.woff2
mkdocs_swan/css/fonts/KFOkCnqEu92Fr1Mu51xLIzIFKw.woff2
mkdocs_swan/css/fonts/KFOkCnqEu92Fr1Mu51xMIzIFKw.woff2
mkdocs_swan/css/fonts/KFOlCnqEu92Fr1MmSU5fABc4EsA.woff2
mkdocs_swan/css/fonts/KFOlCnqEu92Fr1MmSU5fBBc4.woff2
mkdocs_swan/css/fonts/KFOlCnqEu92Fr1MmSU5fBxc4EsA.woff2
mkdocs_swan/css/fonts/KFOlCnqEu92Fr1MmSU5fCBc4EsA.woff2
mkdocs_swan/css/fonts/KFOlCnqEu92Fr1MmSU5fCRc4EsA.woff2
mkdocs_swan/css/fonts/KFOlCnqEu92Fr1MmSU5fChc4EsA.woff2
mkdocs_swan/css/fonts/KFOlCnqEu92Fr1MmSU5fCxc4EsA.woff2
mkdocs_swan/css/fonts/KFOlCnqEu92Fr1MmWUlfABc4EsA.woff2
mkdocs_swan/css/fonts/KFOlCnqEu92Fr1MmWUlfBBc4.woff2
mkdocs_swan/css/fonts/KFOlCnqEu92Fr1MmWUlfBxc4EsA.woff2
mkdocs_swan-0.4.0.dist-info/LICENSE
mkdocs_swan-0.4.0.dist-info/METADATA
mkdocs_swan-0.4.0.dist-info/WHEEL
mkdocs_swan-0.4.0.dist-info/entry_points.txt
mkdocs_swan-0.4.0.dist-info/top_level.txt
mkdocs_swan-0.4.0.dist-info/RECORD
