Metadata-Version: 2.1
Name: mkdocs-swan
Version: 0.4.0
Summary: SWAN theme for MkDocs
Home-page: https://github.com/swan-cern/mkdocs-swan
Author: Diogo Castro
Author-email: diogo.castro@cern.ch
License: BSD
Classifier: Development Status :: 5 - Production/Stable
Classifier: Environment :: Web Environment
Classifier: License :: OSI Approved :: GNU Affero General Public License v3
Classifier: Programming Language :: Python
Classifier: Topic :: Documentation
Classifier: Topic :: Software Development :: Documentation
Classifier: Topic :: Text Processing :: Markup :: HTML
License-File: LICENSE
Requires-Dist: mkdocs-material ==9.*
